deep_learning/__init__.py
deep_learning-0.0.2.dist-info/METADATA
deep_learning-0.0.2.dist-info/RECORD
deep_learning-0.0.2.dist-info/WHEEL
deep_learning-0.0.2.dist-info/top_level.txt
