Metadata-Version: 2.1
Name: deep-learning
Version: 0.0.2
Summary: Cover Mainstream Deep Learning Algorithm
Home-page: https://github.com/itengying/
Author: Bei Zhou
Author-email: spencershuchen@gmail.com
License: UNKNOWN
Platform: UNKNOWN
Classifier: Programming Language :: Python :: 3
Classifier: License :: OSI Approved :: MIT License
Classifier: Operating System :: OS Independent
